pOboto/__init__.py
pOboto/pOcloudWatch.py
pOboto/pOglue.py
pOboto/pOparameterStore.py
pOboto/pOredshiftDataAPIService.py
pOboto/pOs3.py
pOboto/pOsecretsManager.py
pOboto-0.0.4.dist-info/LICENSE
pOboto-0.0.4.dist-info/METADATA
pOboto-0.0.4.dist-info/WHEEL
pOboto-0.0.4.dist-info/top_level.txt
pOboto-0.0.4.dist-info/RECORD
